htbst/__init__.py
htbst/const.py
htbst/htb.py
htbst/labs.py
htbst_replican-0.3.dist-info/METADATA
htbst_replican-0.3.dist-info/WHEEL
htbst_replican-0.3.dist-info/top_level.txt
htbst_replican-0.3.dist-info/RECORD
