Metadata-Version: 2.1
Name: htbst_replican
Version: 0.3
Summary: A htb library
Author: replican
Author-email: replican <fucworldat1337@gmail.com>
Classifier: Programming Language :: Python :: 3
Classifier: License :: OSI Approved :: MIT License
Classifier: Operating System :: OS Independent
Requires-Python: >=3.8
